Nexus/__init__.py
Nexus/exceptions.py
Nexus/models.py
Nexus/scraper.py
Nexus/scrapers/__init__.py
Nexus/scrapers/annatar.py
Nexus/scrapers/apibay.py
Nexus/scrapers/jackett.py
Nexus/scrapers/orionoid.py
Nexus/scrapers/prowlarr.py
Nexus/scrapers/torbox.py
Nexus/scrapers/torrentio.py
nexus_scraper-0.2.3.dist-info/LICENSE
nexus_scraper-0.2.3.dist-info/METADATA
nexus_scraper-0.2.3.dist-info/WHEEL
nexus_scraper-0.2.3.dist-info/RECORD
