Metadata-Version: 2.1
Name: nexus-scraper
Version: 0.2.3
Summary: 
License: MIT
Author: Spoked
Author-email: dreu.lavelle@gmail.com
Requires-Python: >=3.11,<4.0
Classifier: License :: OSI Approved :: MIT License
Classifier: Programming Language :: Python :: 3
Classifier: Programming Language :: Python :: 3.11
Classifier: Programming Language :: Python :: 3.12
Requires-Dist: pydantic (>=2.7.1,<3.0.0)
Requires-Dist: pydantic-settings (>=2.2.1,<3.0.0)
Requires-Dist: requests (>=2.31.0,<3.0.0)
Project-URL: repository, https://github.com/dreulavelle/NexusScraper
